firm_info/__init__.py
firm_info/admin.py
firm_info/apps.py
firm_info/defaults.py
firm_info/exceptions.py
firm_info/factories.py
firm_info/forms.py
firm_info/managers.py
firm_info/models.py
firm_info/serializers.py
firm_info/compat/__init__.py
firm_info/compat/editor_widget.py
firm_info/contrib/__init__.py
firm_info/contrib/django_configuration.py
firm_info/migrations/0001_initial.py
firm_info/migrations/0002_alter_firmcontact_options_alter_firmcontact_address_and_more.py
firm_info/migrations/0003_firmcontact_baseline_firmcontact_short_description_and_more.py
firm_info/migrations/0004_firmcontact_logo_firmcontact_logo_invert.py
firm_info/migrations/0005_firmcontact_favicon.py
firm_info/migrations/0006_alter_firmcontact_options.py
firm_info/migrations/0007_socialsharing_tracking.py
firm_info/migrations/0008_alter_tracking_options.py
firm_info/migrations/0009_alter_socialsharing_options.py
firm_info/migrations/0010_appsbanner.py
firm_info/migrations/0011_alter_firmcontact_favicon_alter_firmcontact_logo_and_more.py
firm_info/migrations/0012_alter_appsbanner_application_type.py
firm_info/migrations/__init__.py
firm_info/templates/baseline.html
firm_info/templates/favicon.html
firm_info/templates/footer_adress.html
firm_info/templates/footer_network.html
firm_info/templates/footer_social_sharing.html
firm_info/templates/header_network.html
firm_info/templates/header_phone.html
firm_info/templates/logo.html
firm_info/templates/logo_i.html
firm_info/templates/og-description.html
firm_info/templates/og-image.html
firm_info/templates/og-twitter-site.html
firm_info/templates/tests/templatetags/firm_info/test_app_banner.html
firm_info/templates/tests/templatetags/firm_info/test_firm_complete_info.html
firm_info/templates/tests/templatetags/firm_info/test_firm_contact.html
firm_info/templates/tests/templatetags/firm_info/test_firm_description.html
firm_info/templates/tests/templatetags/firm_info/test_firm_logos.html
django_firm_info-0.2.7.dist-info/LICENCE.txt
django_firm_info-0.2.7.dist-info/METADATA
django_firm_info-0.2.7.dist-info/WHEEL
django_firm_info-0.2.7.dist-info/top_level.txt
django_firm_info-0.2.7.dist-info/zip-safe
django_firm_info-0.2.7.dist-info/RECORD
