Metadata-Version: 2.2
Name: django-firm-info
Version: 0.2.7
Summary: A Django application package for storage firm info
Home-page: https://github.com/emencia/django-firm-info
Author: Philippe Lafaye
Author-email: lafaye@emencia.com
License: MIT
Project-URL: Source Code, https://github.com/emencia/django-firm-info
Project-URL: Issue Tracker, https://github.com/emencia/django-firm-info/issues
Project-URL: Changelog, https://django-firm-info.readthedocs.io/en/latest/history.html
Project-URL: Documentation, https://django-firm-info.readthedocs.io/
Keywords: Python Django
Classifier: Development Status :: 5 - Production/Stable
Classifier: License :: OSI Approved :: MIT License
Classifier: Operating System :: OS Independent
Classifier: Environment :: Web Environment
Classifier: Programming Language :: Python :: 3
Classifier: Programming Language :: Python :: 3.9
Classifier: Programming Language :: Python :: 3.10
Classifier: Programming Language :: Python :: 3.11
Classifier: Framework :: Django
Classifier: Framework :: Django :: 4.2
Classifier: Framework :: Django :: 5.0
Classifier: Framework :: Django :: 5.1
Classifier: Intended Audience :: Developers
Classifier: Topic :: Internet :: WWW/HTTP
Classifier: Topic :: Software Development :: Libraries :: Python Modules
Requires-Python: >=3.9
License-File: LICENCE.txt
Requires-Dist: Django>=4.2
Requires-Dist: django-smart-media>=0.3.0
Provides-Extra: dev
Requires-Dist: pytest>=7.0.0; extra == "dev"
Requires-Dist: pytest-django>=4.0.0; extra == "dev"
Requires-Dist: factory-boy>=3.3.0; extra == "dev"
Requires-Dist: pyquery>=2.0.0; extra == "dev"
Requires-Dist: freezegun>=1.2.0; extra == "dev"
Provides-Extra: debug
Requires-Dist: django-debug-toolbar>=4.4.0; extra == "debug"
Provides-Extra: quality
Requires-Dist: flake8>=6.0.0; extra == "quality"
Requires-Dist: tox>=4.11.0; extra == "quality"
Provides-Extra: doc
Requires-Dist: sphinx>=8.0.2; extra == "doc"
Requires-Dist: furo>=2024.8.6; extra == "doc"
Requires-Dist: sphinx-copybutton>=0.5.2; extra == "doc"
Provides-Extra: doc-live
Requires-Dist: livereload>=2.6.0; extra == "doc-live"
Provides-Extra: release
Requires-Dist: twine>=5.0.0; extra == "release"
Requires-Dist: gitchangelog; extra == "release"
Requires-Dist: makotemplate; extra == "release"
